{
  "report_date": "2026-07-16",
  "generated_at": "2026-07-15T21:07:27.904000+00:00",
  "story_count": 20,
  "stories": [
    {
      "title": "French MPs approve assisted dying law with strict rules after years of argument",
      "body": "The bill would allow assisted dying for terminally ill adults who meet strict criteria.",
      "source": "BBC World",
      "url": "https://www.bbc.co.uk/news/articles/cvg7g2z4pv3o?at_medium=RSS&at_campaign=rss",
      "published": "Wed, 15 Jul 2026 17:29:26 GMT"
    },
    {
      "title": "Iran threatens to block more trade routes as US launches fresh strikes",
      "body": "US President Donald Trump vowed to strike Iran's bridges and power plants next week if the country does not return to talks.",
      "source": "BBC World",
      "url": "https://www.bbc.co.uk/news/articles/c9323zgq6wvo?at_medium=RSS&at_campaign=rss",
      "published": "Wed, 15 Jul 2026 18:41:21 GMT"
    },
    {
      "title": "Trump retreat over Hormuz tolls suggests he is struggling to end Iran war",
      "body": "The abrupt about-face from the US president was the latest twist in a conflict that has now lasted more than four months.",
      "source": "BBC World",
      "url": "https://www.bbc.co.uk/news/articles/crele3r8j19o?at_medium=RSS&at_campaign=rss",
      "published": "Tue, 14 Jul 2026 23:17:27 GMT"
    },
    {
      "title": "More people around the world now favour China over the US, Pew study suggests",
      "body": "There is more confidence in Xi Jinping than Donald Trump, the US think tank's survey indicates.",
      "source": "BBC World",
      "url": "https://www.bbc.co.uk/news/articles/cd959q11g54o?at_medium=RSS&at_campaign=rss",
      "published": "Wed, 15 Jul 2026 17:02:41 GMT"
    },
    {
      "title": "Russian attacks kill eight as Ukraine hits Black Sea oil tankers",
      "body": "Civilian casualties are reported in four Ukrainian regions, while Kyiv hits 20 Russian vessels in the Black Sea.",
      "source": "BBC World",
      "url": "https://www.bbc.co.uk/news/articles/c8929jv8kdzo?at_medium=RSS&at_campaign=rss",
      "published": "Wed, 15 Jul 2026 13:32:05 GMT"
    },
    {
      "title": "Special police team to investigate killing of an anti-migrant leader in South Africa",
      "body": "The March and March provincial leader died of his injuries in hospital several days after being shot.",
      "source": "BBC World",
      "url": "https://www.bbc.co.uk/news/articles/cm2d2qlgj71o?at_medium=RSS&at_campaign=rss",
      "published": "Wed, 15 Jul 2026 15:33:30 GMT"
    },
    {
      "title": "Five arrested after Hong Kong police raid independent bookshops",
      "body": "Officials say they are suspected of selling \"seditious\" books which incited \"hatred\" against authorities.",
      "source": "BBC World",
      "url": "https://www.bbc.co.uk/news/articles/cq61660qpdpo?at_medium=RSS&at_campaign=rss",
      "published": "Wed, 15 Jul 2026 16:51:07 GMT"
    },
    {
      "title": "Italy's Meloni suffers surprise setback in close vote on electoral reform",
      "body": "The defeat triggered opposition calls for Meloni to resign ahead of next year's general election.",
      "source": "BBC World",
      "url": "https://www.bbc.co.uk/news/articles/c1kykx3vnyyo?at_medium=RSS&at_campaign=rss",
      "published": "Wed, 15 Jul 2026 11:44:28 GMT"
    },
    {
      "title": "Rastafarians in Kenya fail in bid to get cannabis legalised for religious purposes",
      "body": "The court acknowledged the need for a broader national debate on cannabis policy in Kenya.",
      "source": "BBC World",
      "url": "https://www.bbc.co.uk/news/articles/c0lyl5ryyr4o?at_medium=RSS&at_campaign=rss",
      "published": "Wed, 15 Jul 2026 10:50:09 GMT"
    },
    {
      "title": "Venezuela government to launch formal talks with opposition members",
      "body": "The opposition says the aim of the talks is to strengthen the democratic institutions and the electoral system.",
      "source": "BBC World",
      "url": "https://www.bbc.co.uk/news/articles/c1eye5320g5o?at_medium=RSS&at_campaign=rss",
      "published": "Wed, 15 Jul 2026 12:21:21 GMT"
    },
    {
      "title": "China economic growth falls sharply, missing target",
      "body": "Weak demand domestically and the impact of the Iran war on oil prices overshadowed the country's strong exports.",
      "source": "BBC World",
      "url": "https://www.bbc.co.uk/news/articles/cd959x4edy8o?at_medium=RSS&at_campaign=rss",
      "published": "Wed, 15 Jul 2026 10:21:48 GMT"
    },
    {
      "title": "Heatwave prompts Italy's delivery riders to strike for extra rights",
      "body": "Delivery riders in Milan, Bologna and Florence want to protect their health and their wages.",
      "source": "BBC World",
      "url": "https://www.bbc.co.uk/news/articles/c1dydw0r246o?at_medium=RSS&at_campaign=rss",
      "published": "Wed, 15 Jul 2026 11:38:37 GMT"
    },
    {
      "title": "Sierra Leone drops treason charge against ex-president over attempted coup",
      "body": "Ernest Bai Koroma was arrested in 2023 after gunmen broke into an armoury and some jails, freeing inmates.",
      "source": "BBC World",
      "url": "https://www.bbc.co.uk/news/articles/cx2w2k3vklgo?at_medium=RSS&at_campaign=rss",
      "published": "Wed, 15 Jul 2026 11:43:15 GMT"
    },
    {
      "title": "Air India crash report likely to be ready in October, say investigators",
      "body": "The crash killed 260 people, including 241 on board, with only one passenger surviving.",
      "source": "BBC World",
      "url": "https://www.bbc.co.uk/news/articles/cjrgrgx2d9qo?at_medium=RSS&at_campaign=rss",
      "published": "Wed, 15 Jul 2026 09:45:21 GMT"
    },
    {
      "title": "Seven Britons among those killed in Spain wildfires",
      "body": "Twelve of the 13 victims were foreign nationals, Spanish authorities said on Tuesday.",
      "source": "BBC World",
      "url": "https://www.bbc.co.uk/news/articles/cp8l87784ngo?at_medium=RSS&at_campaign=rss",
      "published": "Wed, 15 Jul 2026 12:21:32 GMT"
    },
    {
      "title": "Boss of fake government agency arrested in Nigeria after weeks on the run",
      "body": "The case has gripped Nigeria since President Bola Tinubu ordered a corruption investigation last week.",
      "source": "BBC World",
      "url": "https://www.bbc.co.uk/news/articles/c17y7ykzgrgo?at_medium=RSS&at_campaign=rss",
      "published": "Wed, 15 Jul 2026 09:42:09 GMT"
    },
    {
      "title": "China detains US scientist who studied North Korea nuclear tests",
      "body": "Chen Youlin's family says he has been wrongfully detained for nearly two years on spying charges.",
      "source": "BBC World",
      "url": "https://www.bbc.co.uk/news/articles/cqx1xdn3g4eo?at_medium=RSS&at_campaign=rss",
      "published": "Wed, 15 Jul 2026 02:14:37 GMT"
    },
    {
      "title": "Israeli strike on police post in north Gaza kills seven, officials say",
      "body": "A senior officer in the Hamas-run police force was among those killed in the strike, which Israel's military says targeted \"terrorists\".",
      "source": "BBC World",
      "url": "https://www.bbc.co.uk/news/articles/cqj1jqeyl5ro?at_medium=RSS&at_campaign=rss",
      "published": "Tue, 14 Jul 2026 17:13:27 GMT"
    },
    {
      "title": "Trump pays writer E Jean Carroll $5m in damages over sexual abuse and defamation",
      "body": "The president had sought to delay the payment as he tried to persuade the Supreme Court to overturn the judgement.",
      "source": "BBC World",
      "url": "https://www.bbc.co.uk/news/articles/c2dydj1wp93o?at_medium=RSS&at_campaign=rss",
      "published": "Tue, 14 Jul 2026 17:07:42 GMT"
    },
    {
      "title": "Diamond giant De Beers halts work at flagship South African mine as demand plummets",
      "body": "Production will stop for two years at the mine which employs more than 4,000 people.",
      "source": "BBC World",
      "url": "https://www.bbc.co.uk/news/articles/cjrgr7lr1ejo?at_medium=RSS&at_campaign=rss",
      "published": "Tue, 14 Jul 2026 13:22:09 GMT"
    }
  ],
  "signals": [
    {
      "number": 1,
      "signal_type": "community_report",
      "source": "bbc-world",
      "title": "French MPs approve assisted dying law with strict rules after years of argument",
      "body": "The bill would allow assisted dying for terminally ill adults who meet strict criteria.",
      "labels": [],
      "url": "https://www.bbc.co.uk/news/articles/cvg7g2z4pv3o?at_medium=RSS&at_campaign=rss",
      "published": "Wed, 15 Jul 2026 17:29:26 GMT"
    },
    {
      "number": 2,
      "signal_type": "community_report",
      "source": "bbc-world",
      "title": "Iran threatens to block more trade routes as US launches fresh strikes",
      "body": "US President Donald Trump vowed to strike Iran's bridges and power plants next week if the country does not return to talks.",
      "labels": [],
      "url": "https://www.bbc.co.uk/news/articles/c9323zgq6wvo?at_medium=RSS&at_campaign=rss",
      "published": "Wed, 15 Jul 2026 18:41:21 GMT"
    },
    {
      "number": 3,
      "signal_type": "community_report",
      "source": "bbc-world",
      "title": "Trump retreat over Hormuz tolls suggests he is struggling to end Iran war",
      "body": "The abrupt about-face from the US president was the latest twist in a conflict that has now lasted more than four months.",
      "labels": [],
      "url": "https://www.bbc.co.uk/news/articles/crele3r8j19o?at_medium=RSS&at_campaign=rss",
      "published": "Tue, 14 Jul 2026 23:17:27 GMT"
    },
    {
      "number": 4,
      "signal_type": "community_report",
      "source": "bbc-world",
      "title": "More people around the world now favour China over the US, Pew study suggests",
      "body": "There is more confidence in Xi Jinping than Donald Trump, the US think tank's survey indicates.",
      "labels": [],
      "url": "https://www.bbc.co.uk/news/articles/cd959q11g54o?at_medium=RSS&at_campaign=rss",
      "published": "Wed, 15 Jul 2026 17:02:41 GMT"
    },
    {
      "number": 5,
      "signal_type": "community_report",
      "source": "bbc-world",
      "title": "Russian attacks kill eight as Ukraine hits Black Sea oil tankers",
      "body": "Civilian casualties are reported in four Ukrainian regions, while Kyiv hits 20 Russian vessels in the Black Sea.",
      "labels": [],
      "url": "https://www.bbc.co.uk/news/articles/c8929jv8kdzo?at_medium=RSS&at_campaign=rss",
      "published": "Wed, 15 Jul 2026 13:32:05 GMT"
    },
    {
      "number": 6,
      "signal_type": "community_report",
      "source": "bbc-world",
      "title": "Special police team to investigate killing of an anti-migrant leader in South Africa",
      "body": "The March and March provincial leader died of his injuries in hospital several days after being shot.",
      "labels": [],
      "url": "https://www.bbc.co.uk/news/articles/cm2d2qlgj71o?at_medium=RSS&at_campaign=rss",
      "published": "Wed, 15 Jul 2026 15:33:30 GMT"
    },
    {
      "number": 7,
      "signal_type": "community_report",
      "source": "bbc-world",
      "title": "Five arrested after Hong Kong police raid independent bookshops",
      "body": "Officials say they are suspected of selling \"seditious\" books which incited \"hatred\" against authorities.",
      "labels": [],
      "url": "https://www.bbc.co.uk/news/articles/cq61660qpdpo?at_medium=RSS&at_campaign=rss",
      "published": "Wed, 15 Jul 2026 16:51:07 GMT"
    },
    {
      "number": 8,
      "signal_type": "community_report",
      "source": "bbc-world",
      "title": "Italy's Meloni suffers surprise setback in close vote on electoral reform",
      "body": "The defeat triggered opposition calls for Meloni to resign ahead of next year's general election.",
      "labels": [],
      "url": "https://www.bbc.co.uk/news/articles/c1kykx3vnyyo?at_medium=RSS&at_campaign=rss",
      "published": "Wed, 15 Jul 2026 11:44:28 GMT"
    },
    {
      "number": 9,
      "signal_type": "community_report",
      "source": "bbc-world",
      "title": "Rastafarians in Kenya fail in bid to get cannabis legalised for religious purposes",
      "body": "The court acknowledged the need for a broader national debate on cannabis policy in Kenya.",
      "labels": [],
      "url": "https://www.bbc.co.uk/news/articles/c0lyl5ryyr4o?at_medium=RSS&at_campaign=rss",
      "published": "Wed, 15 Jul 2026 10:50:09 GMT"
    },
    {
      "number": 10,
      "signal_type": "community_report",
      "source": "bbc-world",
      "title": "Venezuela government to launch formal talks with opposition members",
      "body": "The opposition says the aim of the talks is to strengthen the democratic institutions and the electoral system.",
      "labels": [],
      "url": "https://www.bbc.co.uk/news/articles/c1eye5320g5o?at_medium=RSS&at_campaign=rss",
      "published": "Wed, 15 Jul 2026 12:21:21 GMT"
    },
    {
      "number": 11,
      "signal_type": "community_report",
      "source": "bbc-world",
      "title": "China economic growth falls sharply, missing target",
      "body": "Weak demand domestically and the impact of the Iran war on oil prices overshadowed the country's strong exports.",
      "labels": [],
      "url": "https://www.bbc.co.uk/news/articles/cd959x4edy8o?at_medium=RSS&at_campaign=rss",
      "published": "Wed, 15 Jul 2026 10:21:48 GMT"
    },
    {
      "number": 12,
      "signal_type": "community_report",
      "source": "bbc-world",
      "title": "Heatwave prompts Italy's delivery riders to strike for extra rights",
      "body": "Delivery riders in Milan, Bologna and Florence want to protect their health and their wages.",
      "labels": [],
      "url": "https://www.bbc.co.uk/news/articles/c1dydw0r246o?at_medium=RSS&at_campaign=rss",
      "published": "Wed, 15 Jul 2026 11:38:37 GMT"
    },
    {
      "number": 13,
      "signal_type": "community_report",
      "source": "bbc-world",
      "title": "Sierra Leone drops treason charge against ex-president over attempted coup",
      "body": "Ernest Bai Koroma was arrested in 2023 after gunmen broke into an armoury and some jails, freeing inmates.",
      "labels": [],
      "url": "https://www.bbc.co.uk/news/articles/cx2w2k3vklgo?at_medium=RSS&at_campaign=rss",
      "published": "Wed, 15 Jul 2026 11:43:15 GMT"
    },
    {
      "number": 14,
      "signal_type": "community_report",
      "source": "bbc-world",
      "title": "Air India crash report likely to be ready in October, say investigators",
      "body": "The crash killed 260 people, including 241 on board, with only one passenger surviving.",
      "labels": [],
      "url": "https://www.bbc.co.uk/news/articles/cjrgrgx2d9qo?at_medium=RSS&at_campaign=rss",
      "published": "Wed, 15 Jul 2026 09:45:21 GMT"
    },
    {
      "number": 15,
      "signal_type": "community_report",
      "source": "bbc-world",
      "title": "Seven Britons among those killed in Spain wildfires",
      "body": "Twelve of the 13 victims were foreign nationals, Spanish authorities said on Tuesday.",
      "labels": [],
      "url": "https://www.bbc.co.uk/news/articles/cp8l87784ngo?at_medium=RSS&at_campaign=rss",
      "published": "Wed, 15 Jul 2026 12:21:32 GMT"
    },
    {
      "number": 16,
      "signal_type": "community_report",
      "source": "bbc-world",
      "title": "Boss of fake government agency arrested in Nigeria after weeks on the run",
      "body": "The case has gripped Nigeria since President Bola Tinubu ordered a corruption investigation last week.",
      "labels": [],
      "url": "https://www.bbc.co.uk/news/articles/c17y7ykzgrgo?at_medium=RSS&at_campaign=rss",
      "published": "Wed, 15 Jul 2026 09:42:09 GMT"
    },
    {
      "number": 17,
      "signal_type": "community_report",
      "source": "bbc-world",
      "title": "China detains US scientist who studied North Korea nuclear tests",
      "body": "Chen Youlin's family says he has been wrongfully detained for nearly two years on spying charges.",
      "labels": [],
      "url": "https://www.bbc.co.uk/news/articles/cqx1xdn3g4eo?at_medium=RSS&at_campaign=rss",
      "published": "Wed, 15 Jul 2026 02:14:37 GMT"
    },
    {
      "number": 18,
      "signal_type": "community_report",
      "source": "bbc-world",
      "title": "Israeli strike on police post in north Gaza kills seven, officials say",
      "body": "A senior officer in the Hamas-run police force was among those killed in the strike, which Israel's military says targeted \"terrorists\".",
      "labels": [],
      "url": "https://www.bbc.co.uk/news/articles/cqj1jqeyl5ro?at_medium=RSS&at_campaign=rss",
      "published": "Tue, 14 Jul 2026 17:13:27 GMT"
    },
    {
      "number": 19,
      "signal_type": "community_report",
      "source": "bbc-world",
      "title": "Trump pays writer E Jean Carroll $5m in damages over sexual abuse and defamation",
      "body": "The president had sought to delay the payment as he tried to persuade the Supreme Court to overturn the judgement.",
      "labels": [],
      "url": "https://www.bbc.co.uk/news/articles/c2dydj1wp93o?at_medium=RSS&at_campaign=rss",
      "published": "Tue, 14 Jul 2026 17:07:42 GMT"
    },
    {
      "number": 20,
      "signal_type": "community_report",
      "source": "bbc-world",
      "title": "Diamond giant De Beers halts work at flagship South African mine as demand plummets",
      "body": "Production will stop for two years at the mine which employs more than 4,000 people.",
      "labels": [],
      "url": "https://www.bbc.co.uk/news/articles/cjrgr7lr1ejo?at_medium=RSS&at_campaign=rss",
      "published": "Tue, 14 Jul 2026 13:22:09 GMT"
    }
  ],
  "priorities": [
    {
      "signal_id": "https://www.bbc.co.uk/news/articles/cvg7g2z4pv3o?at_medium=RSS&at_campaign=rss",
      "title": "French MPs approve assisted dying law with strict rules after years of argument",
      "source": "",
      "url": "",
      "published": "",
      "classifier_fallback": false,
      "priority_score": 2.70085512164684,
      "contest_score": -1.091510451905363,
      "category": "background_noise",
      "polarity": 1,
      "sign_agreement": 1.0,
      "central_tendency": 0.8755060384536811,
      "contestedness": 0.01213682135019356,
      "impact": 0.5950000000000001,
      "top_clusters": {
        "expression_oriented": 0.9605688242113088,
        "knowledge_oriented": 0.9478540082824527
      },
      "bottom_clusters": {
        "sovereignty_order_oriented": 0.8021978051188954
      },
      "cluster_means": {
        "survival_focused": 0.8569800099328194,
        "stability_seeking": 0.8743865653782262,
        "achievement_oriented": 0.852374368494487,
        "care_oriented": 0.8526361222732763,
        "knowledge_oriented": 0.9478540082824527,
        "governance_oriented": 0.8677836987681944,
        "sovereignty_order_oriented": 0.8021978051188954,
        "expression_oriented": 0.9605688242113088,
        "ecosystem_oriented": 0.8647729436234699
      },
      "priority_raw": 0.46883348359194627,
      "contest_raw": 0.007221408703365169
    },
    {
      "signal_id": "https://www.bbc.co.uk/news/articles/c2dydj1wp93o?at_medium=RSS&at_campaign=rss",
      "title": "Trump pays writer E Jean Carroll $5m in damages over sexual abuse and defamation",
      "source": "",
      "url": "",
      "published": "",
      "classifier_fallback": false,
      "priority_score": 1.8580981689157126,
      "contest_score": -0.9313853555661555,
      "category": "background_noise",
      "polarity": 1,
      "sign_agreement": 1.0,
      "central_tendency": 0.7539984297943753,
      "contestedness": 0.018026536642711366,
      "impact": 0.605,
      "top_clusters": {
        "knowledge_oriented": 0.8274724750901767,
        "expression_oriented": 0.8242643314396653
      },
      "bottom_clusters": {
        "care_oriented": 0.7052919865583249
      },
      "cluster_means": {
        "survival_focused": 0.7323707902169238,
        "stability_seeking": 0.7692066391678622,
        "achievement_oriented": 0.7328432060514304,
        "care_oriented": 0.7052919865583249,
        "knowledge_oriented": 0.8274724750901767,
        "governance_oriented": 0.7508697426941418,
        "sovereignty_order_oriented": 0.715753878905468,
        "expression_oriented": 0.8242643314396653,
        "ecosystem_oriented": 0.7279128180253829
      },
      "priority_raw": 0.36493524002047767,
      "contest_raw": 0.010906054668840376
    },
    {
      "signal_id": "https://www.bbc.co.uk/news/articles/c1eye5320g5o?at_medium=RSS&at_campaign=rss",
      "title": "Venezuela government to launch formal talks with opposition members",
      "source": "",
      "url": "",
      "published": "",
      "classifier_fallback": false,
      "priority_score": 1.6973943497202002,
      "contest_score": -0.2639507079054021,
      "category": "background_noise",
      "polarity": 1,
      "sign_agreement": 1.0,
      "central_tendency": 0.8964235568506395,
      "contestedness": 0.04775349832893605,
      "impact": 0.55,
      "top_clusters": {
        "governance_oriented": 0.9763618452907932,
        "stability_seeking": 0.9585993814079519
      },
      "bottom_clusters": {
        "ecosystem_oriented": 0.8029201601595465
      },
      "cluster_means": {
        "survival_focused": 0.9105875487925617,
        "stability_seeking": 0.9585993814079519,
        "achievement_oriented": 0.9090664140754662,
        "care_oriented": 0.9259986447246632,
        "knowledge_oriented": 0.8613129157465301,
        "governance_oriented": 0.9763618452907932,
        "sovereignty_order_oriented": 0.9046641393738102,
        "expression_oriented": 0.8183009620844325,
        "ecosystem_oriented": 0.8029201601595465
      },
      "priority_raw": 0.3451230693874962,
      "contest_raw": 0.02626442408091483
    },
    {
      "signal_id": "https://www.bbc.co.uk/news/articles/c17y7ykzgrgo?at_medium=RSS&at_campaign=rss",
      "title": "Boss of fake government agency arrested in Nigeria after weeks on the run",
      "source": "",
      "url": "",
      "published": "",
      "classifier_fallback": false,
      "priority_score": 1.1199508766040707,
      "contest_score": -0.4069012431470118,
      "category": "background_noise",
      "polarity": 1,
      "sign_agreement": 1.0,
      "central_tendency": 0.8696306934252548,
      "contestedness": 0.05105551718162049,
      "impact": 0.45,
      "top_clusters": {
        "governance_oriented": 0.9740531700869999,
        "stability_seeking": 0.9361889950648559
      },
      "bottom_clusters": {
        "ecosystem_oriented": 0.78567205236618
      },
      "cluster_means": {
        "survival_focused": 0.8651814402159046,
        "stability_seeking": 0.9361889950648559,
        "achievement_oriented": 0.8440342786135195,
        "care_oriented": 0.9074275429182657,
        "knowledge_oriented": 0.8527756185308846,
        "governance_oriented": 0.9740531700869999,
        "sovereignty_order_oriented": 0.8563720257366452,
        "expression_oriented": 0.8049711172940371,
        "ecosystem_oriented": 0.78567205236618
      },
      "priority_raw": 0.2739336684289552,
      "contest_raw": 0.02297498273172922
    },
    {
      "signal_id": "https://www.bbc.co.uk/news/articles/cjrgrgx2d9qo?at_medium=RSS&at_campaign=rss",
      "title": "Air India crash report likely to be ready in October, say investigators",
      "source": "",
      "url": "",
      "published": "",
      "classifier_fallback": false,
      "priority_score": 0.19969084019705347,
      "contest_score": 1.8722841713640797,
      "category": "background_noise",
      "polarity": 1,
      "sign_agreement": 1.0,
      "central_tendency": 0.31841379663563824,
      "contestedness": 0.08978740864219059,
      "impact": 0.8400000000000001,
      "top_clusters": {
        "expression_oriented": 0.5063203217218288,
        "knowledge_oriented": 0.439079380032491
      },
      "bottom_clusters": {
        "survival_focused": 0.19378895225917994
      },
      "cluster_means": {
        "survival_focused": 0.19378895225917994,
        "stability_seeking": 0.21956141407317994,
        "achievement_oriented": 0.3519353203096414,
        "care_oriented": 0.30758781786053035,
        "knowledge_oriented": 0.439079380032491,
        "governance_oriented": 0.2541782191542494,
        "sovereignty_order_oriented": 0.19589751780692255,
        "expression_oriented": 0.5063203217218288,
        "ecosystem_oriented": 0.39737522650272095
      },
      "priority_raw": 0.1604805535043617,
      "contest_raw": 0.07542142325944011
    },
    {
      "signal_id": "https://www.bbc.co.uk/news/articles/cm2d2qlgj71o?at_medium=RSS&at_campaign=rss",
      "title": "Special police team to investigate killing of an anti-migrant leader in South Africa",
      "source": "",
      "url": "",
      "published": "",
      "classifier_fallback": false,
      "priority_score": -0.07161299823428774,
      "contest_score": 1.1307954995450142,
      "category": "background_noise",
      "polarity": 1,
      "sign_agreement": 1.0,
      "central_tendency": 0.23722352371493777,
      "contestedness": 0.07628626573508354,
      "impact": 0.765,
      "top_clusters": {
        "expression_oriented": 0.4545295323922408,
        "knowledge_oriented": 0.3903787498935486
      },
      "bottom_clusters": {
        "survival_focused": 0.10400049127767602
      },
      "cluster_means": {
        "survival_focused": 0.10400049127767602,
        "stability_seeking": 0.14793534374921888,
        "achievement_oriented": 0.253014075703377,
        "care_oriented": 0.19389308397105015,
        "knowledge_oriented": 0.3903787498935486,
        "governance_oriented": 0.16725860016684366,
        "sovereignty_order_oriented": 0.11760681823596661,
        "expression_oriented": 0.4545295323922408,
        "ecosystem_oriented": 0.30639501804451824
      },
      "priority_raw": 0.12703319694934917,
      "contest_raw": 0.05835899328733891
    },
    {
      "signal_id": "https://www.bbc.co.uk/news/articles/c1dydw0r246o?at_medium=RSS&at_campaign=rss",
      "title": "Heatwave prompts Italy's delivery riders to strike for extra rights",
      "source": "",
      "url": "",
      "published": "",
      "classifier_fallback": false,
      "priority_score": -0.09364312669105827,
      "contest_score": 2.5496661126950713,
      "category": "background_noise",
      "polarity": 1,
      "sign_agreement": 1.0,
      "central_tendency": 0.3801750456903797,
      "contestedness": 0.16698842257655805,
      "impact": 0.545,
      "top_clusters": {
        "expression_oriented": 0.6299571914957977,
        "care_oriented": 0.5924492517285647
      },
      "bottom_clusters": {
        "sovereignty_order_oriented": 0.1059042226876808
      },
      "cluster_means": {
        "survival_focused": 0.17820679357649077,
        "stability_seeking": 0.2698797171119947,
        "achievement_oriented": 0.21176636685217376,
        "care_oriented": 0.5924492517285647,
        "knowledge_oriented": 0.5454307663551198,
        "governance_oriented": 0.4254608291520066,
        "sovereignty_order_oriented": 0.1059042226876808,
        "expression_oriented": 0.6299571914957977,
        "ecosystem_oriented": 0.46252027225358866
      },
      "priority_raw": 0.12431723994075415,
      "contest_raw": 0.09100869030422415
    },
    {
      "signal_id": "https://www.bbc.co.uk/news/articles/cx2w2k3vklgo?at_medium=RSS&at_campaign=rss",
      "title": "Sierra Leone drops treason charge against ex-president over attempted coup",
      "source": "",
      "url": "",
      "published": "",
      "classifier_fallback": false,
      "priority_score": -0.12548646477045775,
      "contest_score": -1.1315239241160353,
      "category": "background_noise",
      "polarity": 1,
      "sign_agreement": 1.0,
      "central_tendency": 0.4864301962800547,
      "contestedness": 0.012728599700488341,
      "impact": 0.495,
      "top_clusters": {
        "stability_seeking": 0.5137847394378801,
        "achievement_oriented": 0.5092358298042656
      },
      "bottom_clusters": {
        "ecosystem_oriented": 0.4252045326279138
      },
      "cluster_means": {
        "survival_focused": 0.5010561397373917,
        "stability_seeking": 0.5137847394378801,
        "achievement_oriented": 0.5092358298042656,
        "care_oriented": 0.4841028086528224,
        "knowledge_oriented": 0.5045672672513503,
        "governance_oriented": 0.4599853568221999,
        "sovereignty_order_oriented": 0.4763295530196611,
        "expression_oriented": 0.5036055391670073,
        "ecosystem_oriented": 0.4252045326279138
      },
      "priority_raw": 0.12039147357931353,
      "contest_raw": 0.006300656851741729
    },
    {
      "signal_id": "https://www.bbc.co.uk/news/articles/cd959q11g54o?at_medium=RSS&at_campaign=rss",
      "title": "More people around the world now favour China over the US, Pew study suggests",
      "source": "",
      "url": "",
      "published": "",
      "classifier_fallback": false,
      "priority_score": -0.16846873209351831,
      "contest_score": -0.9031019648563278,
      "category": "background_noise",
      "polarity": 1,
      "sign_agreement": 1.0,
      "central_tendency": 0.5587012532480669,
      "contestedness": 0.02244055354347263,
      "impact": 0.515,
      "top_clusters": {
        "achievement_oriented": 0.6175306524626333,
        "stability_seeking": 0.5790952824201957
      },
      "bottom_clusters": {
        "ecosystem_oriented": 0.5271353205094655
      },
      "cluster_means": {
        "survival_focused": 0.5311453152168433,
        "stability_seeking": 0.5790952824201957,
        "achievement_oriented": 0.6175306524626333,
        "care_oriented": 0.5564471887082583,
        "knowledge_oriented": 0.5696895192581397,
        "governance_oriented": 0.5531143915001435,
        "sovereignty_order_oriented": 0.5340066351647856,
        "expression_oriented": 0.5601469739921372,
        "ecosystem_oriented": 0.5271353205094655
      },
      "priority_raw": 0.1150924581691018,
      "contest_raw": 0.011556885074888404
    },
    {
      "signal_id": "https://www.bbc.co.uk/news/articles/c8929jv8kdzo?at_medium=RSS&at_campaign=rss",
      "title": "Russian attacks kill eight as Ukraine hits Black Sea oil tankers",
      "source": "",
      "url": "",
      "published": "",
      "classifier_fallback": false,
      "priority_score": -0.40125961903886065,
      "contest_score": 0.1703438706675914,
      "category": "background_noise",
      "polarity": 1,
      "sign_agreement": 1.0,
      "central_tendency": 0.17559577840573778,
      "contestedness": 0.044217069057713,
      "impact": 0.8200000000000001,
      "top_clusters": {
        "expression_oriented": 0.2880752818343226,
        "knowledge_oriented": 0.26384963394358985
      },
      "bottom_clusters": {
        "survival_focused": 0.07229915807020118
      },
      "cluster_means": {
        "survival_focused": 0.07229915807020118,
        "stability_seeking": 0.11078649023228732,
        "achievement_oriented": 0.1995383434028797,
        "care_oriented": 0.15413200207254546,
        "knowledge_oriented": 0.26384963394358985,
        "governance_oriented": 0.1553212743451667,
        "sovereignty_order_oriented": 0.13821590607363468,
        "expression_oriented": 0.2880752818343226,
        "ecosystem_oriented": 0.19814391567701245
      },
      "priority_raw": 0.086393122975623,
      "contest_raw": 0.036257996627324665
    },
    {
      "signal_id": "https://www.bbc.co.uk/news/articles/cjrgr7lr1ejo?at_medium=RSS&at_campaign=rss",
      "title": "Diamond giant De Beers halts work at flagship South African mine as demand plummets",
      "source": "",
      "url": "",
      "published": "",
      "classifier_fallback": false,
      "priority_score": -0.41469509019348116,
      "contest_score": -0.24314861049496947,
      "category": "background_noise",
      "polarity": 1,
      "sign_agreement": 1.0,
      "central_tendency": 0.2321554729079819,
      "contestedness": 0.03663438644156683,
      "impact": 0.73,
      "top_clusters": {
        "expression_oriented": 0.37840407551386657,
        "knowledge_oriented": 0.33237297787931747
      },
      "bottom_clusters": {
        "survival_focused": 0.13191666943770144
      },
      "cluster_means": {
        "survival_focused": 0.13191666943770144,
        "stability_seeking": 0.17314397316628755,
        "achievement_oriented": 0.19047056024842735,
        "care_oriented": 0.23672417532613788,
        "knowledge_oriented": 0.33237297787931747,
        "governance_oriented": 0.2040114839980342,
        "sovereignty_order_oriented": 0.16737709755646737,
        "expression_oriented": 0.37840407551386657,
        "ecosystem_oriented": 0.2749782430455976
      },
      "priority_raw": 0.0847367476114134,
      "contest_raw": 0.026743102102343784
    },
    {
      "signal_id": "https://www.bbc.co.uk/news/articles/cqj1jqeyl5ro?at_medium=RSS&at_campaign=rss",
      "title": "Israeli strike on police post in north Gaza kills seven, officials say",
      "source": "",
      "url": "",
      "published": "",
      "classifier_fallback": false,
      "priority_score": -0.4189798873774179,
      "contest_score": 0.9954126620160456,
      "category": "background_noise",
      "polarity": 1,
      "sign_agreement": 0.9722222222222222,
      "central_tendency": 0.17115549129181545,
      "contestedness": 0.06737035680329806,
      "impact": 0.8200000000000001,
      "top_clusters": {
        "expression_oriented": 0.3582806027927901,
        "knowledge_oriented": 0.2935488085760071
      },
      "bottom_clusters": {
        "survival_focused": 0.05264964929424429
      },
      "cluster_means": {
        "survival_focused": 0.05264964929424429,
        "stability_seeking": 0.08260463795042966,
        "achievement_oriented": 0.14919940025937323,
        "care_oriented": 0.1657936042894323,
        "knowledge_oriented": 0.2935488085760071,
        "governance_oriented": 0.10943262321064207,
        "sovereignty_order_oriented": 0.08182904345607517,
        "expression_oriented": 0.3582806027927901,
        "ecosystem_oriented": 0.23433123259693747
      },
      "priority_raw": 0.0842085017155732,
      "contest_raw": 0.055243692578704415
    },
    {
      "signal_id": "https://www.bbc.co.uk/news/articles/crele3r8j19o?at_medium=RSS&at_campaign=rss",
      "title": "Trump retreat over Hormuz tolls suggests he is struggling to end Iran war",
      "source": "",
      "url": "",
      "published": "",
      "classifier_fallback": false,
      "priority_score": -0.5036923162137527,
      "contest_score": 0.2855152057915905,
      "category": "background_noise",
      "polarity": 1,
      "sign_agreement": 1.0,
      "central_tendency": 0.290412737022993,
      "contestedness": 0.06127277090298783,
      "impact": 0.635,
      "top_clusters": {
        "expression_oriented": 0.4266308880032995,
        "knowledge_oriented": 0.3897751250855114
      },
      "bottom_clusters": {
        "sovereignty_order_oriented": 0.2064284180207821
      },
      "cluster_means": {
        "survival_focused": 0.21169560521011768,
        "stability_seeking": 0.2373510581794536,
        "achievement_oriented": 0.3082194802907754,
        "care_oriented": 0.3025075669137821,
        "knowledge_oriented": 0.3897751250855114,
        "governance_oriented": 0.23491686030011344,
        "sovereignty_order_oriented": 0.2064284180207821,
        "expression_oriented": 0.4266308880032995,
        "ecosystem_oriented": 0.29618963120310127
      },
      "priority_raw": 0.07376483520384022,
      "contest_raw": 0.03890820952339727
    },
    {
      "signal_id": "https://www.bbc.co.uk/news/articles/c9323zgq6wvo?at_medium=RSS&at_campaign=rss",
      "title": "Iran threatens to block more trade routes as US launches fresh strikes",
      "source": "",
      "url": "",
      "published": "",
      "classifier_fallback": false,
      "priority_score": -0.5683632660280056,
      "contest_score": 0.9302704090176456,
      "category": "background_noise",
      "polarity": 1,
      "sign_agreement": 0.9166666666666666,
      "central_tendency": 0.1388015981573077,
      "contestedness": 0.06803126733571807,
      "impact": 0.79,
      "top_clusters": {
        "expression_oriented": 0.2852660302202419,
        "knowledge_oriented": 0.23576978486222855
      },
      "bottom_clusters": {
        "survival_focused": 0.028708905105104404
      },
      "cluster_means": {
        "survival_focused": 0.028708905105104404,
        "stability_seeking": 0.04212493942326656,
        "achievement_oriented": 0.11950222680117215,
        "care_oriented": 0.1645601154432031,
        "knowledge_oriented": 0.23576978486222855,
        "governance_oriented": 0.09925887202772649,
        "sovereignty_order_oriented": 0.05846712890672681,
        "expression_oriented": 0.2852660302202419,
        "ecosystem_oriented": 0.18753349413689022
      },
      "priority_raw": 0.06579195752656385,
      "contest_raw": 0.05374470119521728
    },
    {
      "signal_id": "https://www.bbc.co.uk/news/articles/c1kykx3vnyyo?at_medium=RSS&at_campaign=rss",
      "title": "Italy's Meloni suffers surprise setback in close vote on electoral reform",
      "source": "",
      "url": "",
      "published": "",
      "classifier_fallback": false,
      "priority_score": -0.6465901557132921,
      "contest_score": -0.7352867463175885,
      "category": "background_noise",
      "polarity": 1,
      "sign_agreement": 1.0,
      "central_tendency": 0.2752345718092586,
      "contestedness": 0.030232330973372745,
      "impact": 0.51,
      "top_clusters": {
        "expression_oriented": 0.37726648762513976,
        "knowledge_oriented": 0.3537038877161134
      },
      "bottom_clusters": {
        "sovereignty_order_oriented": 0.22009439701767133
      },
      "cluster_means": {
        "survival_focused": 0.23573661080617803,
        "stability_seeking": 0.26596894177955077,
        "achievement_oriented": 0.2821832659391785,
        "care_oriented": 0.2763583766026047,
        "knowledge_oriented": 0.3537038877161134,
        "governance_oriented": 0.22333972232320093,
        "sovereignty_order_oriented": 0.22009439701767133,
        "expression_oriented": 0.37726648762513976,
        "ecosystem_oriented": 0.2424594564736901
      },
      "priority_raw": 0.05614785264908875,
      "contest_raw": 0.015418488796420101
    },
    {
      "signal_id": "https://www.bbc.co.uk/news/articles/cd959x4edy8o?at_medium=RSS&at_campaign=rss",
      "title": "China economic growth falls sharply, missing target",
      "source": "",
      "url": "",
      "published": "",
      "classifier_fallback": false,
      "priority_score": -0.689767933231723,
      "contest_score": -0.1665104424606261,
      "category": "background_noise",
      "polarity": 1,
      "sign_agreement": 1.0,
      "central_tendency": 0.18414758698338168,
      "contestedness": 0.041313951472607746,
      "impact": 0.6900000000000001,
      "top_clusters": {
        "expression_oriented": 0.3279396534602834,
        "knowledge_oriented": 0.28155371657513956
      },
      "bottom_clusters": {
        "survival_focused": 0.10059227921734523
      },
      "cluster_means": {
        "survival_focused": 0.10059227921734523,
        "stability_seeking": 0.12658293779004492,
        "achievement_oriented": 0.13770300865292096,
        "care_oriented": 0.2328964997643826,
        "knowledge_oriented": 0.28155371657513956,
        "governance_oriented": 0.15074697300038456,
        "sovereignty_order_oriented": 0.10943302152777681,
        "expression_oriented": 0.3279396534602834,
        "ecosystem_oriented": 0.18988019286215702
      },
      "priority_raw": 0.05082473400741336,
      "contest_raw": 0.028506626516099347
    },
    {
      "signal_id": "https://www.bbc.co.uk/news/articles/cp8l87784ngo?at_medium=RSS&at_campaign=rss",
      "title": "Seven Britons among those killed in Spain wildfires",
      "source": "",
      "url": "",
      "published": "",
      "classifier_fallback": false,
      "priority_score": -0.7864123809295828,
      "contest_score": -0.22487469298778756,
      "category": "background_noise",
      "polarity": 1,
      "sign_agreement": 0.9722222222222222,
      "central_tendency": 0.09976934199741602,
      "contestedness": 0.03482513340974189,
      "impact": 0.78,
      "top_clusters": {
        "expression_oriented": 0.20196746074483518,
        "knowledge_oriented": 0.1778624216429648
      },
      "bottom_clusters": {
        "survival_focused": 0.04002735279636757
      },
      "cluster_means": {
        "survival_focused": 0.04002735279636757,
        "stability_seeking": 0.042890911358260925,
        "achievement_oriented": 0.11736011841704527,
        "care_oriented": 0.08253498500730339,
        "knowledge_oriented": 0.1778624216429648,
        "governance_oriented": 0.05767001510874259,
        "sovereignty_order_oriented": 0.08013926245364422,
        "expression_oriented": 0.20196746074483518,
        "ecosystem_oriented": 0.09073867547941103
      },
      "priority_raw": 0.03891004337899225,
      "contest_raw": 0.027163604059598674
    },
    {
      "signal_id": "https://www.bbc.co.uk/news/articles/c0lyl5ryyr4o?at_medium=RSS&at_campaign=rss",
      "title": "Rastafarians in Kenya fail in bid to get cannabis legalised for religious purposes",
      "source": "",
      "url": "",
      "published": "",
      "classifier_fallback": false,
      "priority_score": -0.8029963179920073,
      "contest_score": -1.1366421380889915,
      "category": "background_noise",
      "polarity": 1,
      "sign_agreement": 1.0,
      "central_tendency": 0.2671414007835622,
      "contestedness": 0.017921395345857905,
      "impact": 0.345,
      "top_clusters": {
        "expression_oriented": 0.30226100204209816,
        "knowledge_oriented": 0.29680350908576913
      },
      "bottom_clusters": {
        "sovereignty_order_oriented": 0.22420381923172428
      },
      "cluster_means": {
        "survival_focused": 0.23176486678115504,
        "stability_seeking": 0.2832376690801317,
        "achievement_oriented": 0.2626452597789992,
        "care_oriented": 0.2870905851107633,
        "knowledge_oriented": 0.29680350908576913,
        "governance_oriented": 0.27888211373991123,
        "sovereignty_order_oriented": 0.22420381923172428,
        "expression_oriented": 0.30226100204209816,
        "ecosystem_oriented": 0.23738378220150722
      },
      "priority_raw": 0.036865513308131585,
      "contest_raw": 0.006182881394320976
    },
    {
      "signal_id": "https://www.bbc.co.uk/news/articles/cqx1xdn3g4eo?at_medium=RSS&at_campaign=rss",
      "title": "China detains US scientist who studied North Korea nuclear tests",
      "source": "",
      "url": "",
      "published": "",
      "classifier_fallback": false,
      "priority_score": -0.9075811450010589,
      "contest_score": -0.08178449777479035,
      "category": "background_noise",
      "polarity": 1,
      "sign_agreement": 0.9166666666666666,
      "central_tendency": 0.0838178422528979,
      "contestedness": 0.0425961666165274,
      "impact": 0.715,
      "top_clusters": {
        "expression_oriented": 0.15835460427096618,
        "care_oriented": 0.13331494756605916
      },
      "bottom_clusters": {
        "achievement_oriented": 0.014899321955156891
      },
      "cluster_means": {
        "survival_focused": 0.04694781944580009,
        "stability_seeking": 0.04803447859377827,
        "achievement_oriented": 0.014899321955156891,
        "care_oriented": 0.13331494756605916,
        "knowledge_oriented": 0.10910010155917671,
        "governance_oriented": 0.04101709431514278,
        "sovereignty_order_oriented": 0.0665039349426493,
        "expression_oriented": 0.15835460427096618,
        "ecosystem_oriented": 0.11983647004962539
      },
      "priority_raw": 0.0239719028843288,
      "contest_raw": 0.030456259130817093
    },
    {
      "signal_id": "https://www.bbc.co.uk/news/articles/cq61660qpdpo?at_medium=RSS&at_campaign=rss",
      "title": "Five arrested after Hong Kong police raid independent bookshops",
      "source": "",
      "url": "",
      "published": "",
      "classifier_fallback": false,
      "priority_score": -0.9764399235753712,
      "contest_score": -0.6176671554759876,
      "category": "background_noise",
      "polarity": 1,
      "sign_agreement": 0.9444444444444444,
      "central_tendency": 0.059094404361989726,
      "contestedness": 0.027671814683283003,
      "impact": 0.655,
      "top_clusters": {
        "expression_oriented": 0.10562423070425711,
        "ecosystem_oriented": 0.09333439125294798
      },
      "bottom_clusters": {
        "governance_oriented": 0.002724430309751419
      },
      "cluster_means": {
        "survival_focused": 0.03677247193120378,
        "stability_seeking": 0.03883149559785548,
        "achievement_oriented": 0.02215996265262049,
        "care_oriented": 0.06944391897492044,
        "knowledge_oriented": 0.06792815064579943,
        "governance_oriented": 0.002724430309751419,
        "sovereignty_order_oriented": 0.06650331028113848,
        "expression_oriented": 0.10562423070425711,
        "ecosystem_oriented": 0.09333439125294798
      },
      "priority_raw": 0.01548273394284131,
      "contest_raw": 0.018125038617550368
    }
  ],
  "selected_priorities": [
    {
      "signal_id": "https://www.bbc.co.uk/news/articles/cvg7g2z4pv3o?at_medium=RSS&at_campaign=rss",
      "title": "French MPs approve assisted dying law with strict rules after years of argument",
      "source": "",
      "url": "",
      "published": "",
      "classifier_fallback": false,
      "priority_score": 2.70085512164684,
      "contest_score": -1.091510451905363,
      "category": "background_noise",
      "polarity": 1,
      "sign_agreement": 1.0,
      "central_tendency": 0.8755060384536811,
      "contestedness": 0.01213682135019356,
      "impact": 0.5950000000000001,
      "top_clusters": {
        "expression_oriented": 0.9605688242113088,
        "knowledge_oriented": 0.9478540082824527
      },
      "bottom_clusters": {
        "sovereignty_order_oriented": 0.8021978051188954
      },
      "cluster_means": {
        "survival_focused": 0.8569800099328194,
        "stability_seeking": 0.8743865653782262,
        "achievement_oriented": 0.852374368494487,
        "care_oriented": 0.8526361222732763,
        "knowledge_oriented": 0.9478540082824527,
        "governance_oriented": 0.8677836987681944,
        "sovereignty_order_oriented": 0.8021978051188954,
        "expression_oriented": 0.9605688242113088,
        "ecosystem_oriented": 0.8647729436234699
      },
      "priority_raw": 0.46883348359194627,
      "contest_raw": 0.007221408703365169
    },
    {
      "signal_id": "https://www.bbc.co.uk/news/articles/c2dydj1wp93o?at_medium=RSS&at_campaign=rss",
      "title": "Trump pays writer E Jean Carroll $5m in damages over sexual abuse and defamation",
      "source": "",
      "url": "",
      "published": "",
      "classifier_fallback": false,
      "priority_score": 1.8580981689157126,
      "contest_score": -0.9313853555661555,
      "category": "background_noise",
      "polarity": 1,
      "sign_agreement": 1.0,
      "central_tendency": 0.7539984297943753,
      "contestedness": 0.018026536642711366,
      "impact": 0.605,
      "top_clusters": {
        "knowledge_oriented": 0.8274724750901767,
        "expression_oriented": 0.8242643314396653
      },
      "bottom_clusters": {
        "care_oriented": 0.7052919865583249
      },
      "cluster_means": {
        "survival_focused": 0.7323707902169238,
        "stability_seeking": 0.7692066391678622,
        "achievement_oriented": 0.7328432060514304,
        "care_oriented": 0.7052919865583249,
        "knowledge_oriented": 0.8274724750901767,
        "governance_oriented": 0.7508697426941418,
        "sovereignty_order_oriented": 0.715753878905468,
        "expression_oriented": 0.8242643314396653,
        "ecosystem_oriented": 0.7279128180253829
      },
      "priority_raw": 0.36493524002047767,
      "contest_raw": 0.010906054668840376
    },
    {
      "signal_id": "https://www.bbc.co.uk/news/articles/c1eye5320g5o?at_medium=RSS&at_campaign=rss",
      "title": "Venezuela government to launch formal talks with opposition members",
      "source": "",
      "url": "",
      "published": "",
      "classifier_fallback": false,
      "priority_score": 1.6973943497202002,
      "contest_score": -0.2639507079054021,
      "category": "background_noise",
      "polarity": 1,
      "sign_agreement": 1.0,
      "central_tendency": 0.8964235568506395,
      "contestedness": 0.04775349832893605,
      "impact": 0.55,
      "top_clusters": {
        "governance_oriented": 0.9763618452907932,
        "stability_seeking": 0.9585993814079519
      },
      "bottom_clusters": {
        "ecosystem_oriented": 0.8029201601595465
      },
      "cluster_means": {
        "survival_focused": 0.9105875487925617,
        "stability_seeking": 0.9585993814079519,
        "achievement_oriented": 0.9090664140754662,
        "care_oriented": 0.9259986447246632,
        "knowledge_oriented": 0.8613129157465301,
        "governance_oriented": 0.9763618452907932,
        "sovereignty_order_oriented": 0.9046641393738102,
        "expression_oriented": 0.8183009620844325,
        "ecosystem_oriented": 0.8029201601595465
      },
      "priority_raw": 0.3451230693874962,
      "contest_raw": 0.02626442408091483
    },
    {
      "signal_id": "https://www.bbc.co.uk/news/articles/c17y7ykzgrgo?at_medium=RSS&at_campaign=rss",
      "title": "Boss of fake government agency arrested in Nigeria after weeks on the run",
      "source": "",
      "url": "",
      "published": "",
      "classifier_fallback": false,
      "priority_score": 1.1199508766040707,
      "contest_score": -0.4069012431470118,
      "category": "background_noise",
      "polarity": 1,
      "sign_agreement": 1.0,
      "central_tendency": 0.8696306934252548,
      "contestedness": 0.05105551718162049,
      "impact": 0.45,
      "top_clusters": {
        "governance_oriented": 0.9740531700869999,
        "stability_seeking": 0.9361889950648559
      },
      "bottom_clusters": {
        "ecosystem_oriented": 0.78567205236618
      },
      "cluster_means": {
        "survival_focused": 0.8651814402159046,
        "stability_seeking": 0.9361889950648559,
        "achievement_oriented": 0.8440342786135195,
        "care_oriented": 0.9074275429182657,
        "knowledge_oriented": 0.8527756185308846,
        "governance_oriented": 0.9740531700869999,
        "sovereignty_order_oriented": 0.8563720257366452,
        "expression_oriented": 0.8049711172940371,
        "ecosystem_oriented": 0.78567205236618
      },
      "priority_raw": 0.2739336684289552,
      "contest_raw": 0.02297498273172922
    },
    {
      "signal_id": "https://www.bbc.co.uk/news/articles/cjrgrgx2d9qo?at_medium=RSS&at_campaign=rss",
      "title": "Air India crash report likely to be ready in October, say investigators",
      "source": "",
      "url": "",
      "published": "",
      "classifier_fallback": false,
      "priority_score": 0.19969084019705347,
      "contest_score": 1.8722841713640797,
      "category": "background_noise",
      "polarity": 1,
      "sign_agreement": 1.0,
      "central_tendency": 0.31841379663563824,
      "contestedness": 0.08978740864219059,
      "impact": 0.8400000000000001,
      "top_clusters": {
        "expression_oriented": 0.5063203217218288,
        "knowledge_oriented": 0.439079380032491
      },
      "bottom_clusters": {
        "survival_focused": 0.19378895225917994
      },
      "cluster_means": {
        "survival_focused": 0.19378895225917994,
        "stability_seeking": 0.21956141407317994,
        "achievement_oriented": 0.3519353203096414,
        "care_oriented": 0.30758781786053035,
        "knowledge_oriented": 0.439079380032491,
        "governance_oriented": 0.2541782191542494,
        "sovereignty_order_oriented": 0.19589751780692255,
        "expression_oriented": 0.5063203217218288,
        "ecosystem_oriented": 0.39737522650272095
      },
      "priority_raw": 0.1604805535043617,
      "contest_raw": 0.07542142325944011
    },
    {
      "signal_id": "https://www.bbc.co.uk/news/articles/cm2d2qlgj71o?at_medium=RSS&at_campaign=rss",
      "title": "Special police team to investigate killing of an anti-migrant leader in South Africa",
      "source": "",
      "url": "",
      "published": "",
      "classifier_fallback": false,
      "priority_score": -0.07161299823428774,
      "contest_score": 1.1307954995450142,
      "category": "background_noise",
      "polarity": 1,
      "sign_agreement": 1.0,
      "central_tendency": 0.23722352371493777,
      "contestedness": 0.07628626573508354,
      "impact": 0.765,
      "top_clusters": {
        "expression_oriented": 0.4545295323922408,
        "knowledge_oriented": 0.3903787498935486
      },
      "bottom_clusters": {
        "survival_focused": 0.10400049127767602
      },
      "cluster_means": {
        "survival_focused": 0.10400049127767602,
        "stability_seeking": 0.14793534374921888,
        "achievement_oriented": 0.253014075703377,
        "care_oriented": 0.19389308397105015,
        "knowledge_oriented": 0.3903787498935486,
        "governance_oriented": 0.16725860016684366,
        "sovereignty_order_oriented": 0.11760681823596661,
        "expression_oriented": 0.4545295323922408,
        "ecosystem_oriented": 0.30639501804451824
      },
      "priority_raw": 0.12703319694934917,
      "contest_raw": 0.05835899328733891
    },
    {
      "signal_id": "https://www.bbc.co.uk/news/articles/c1dydw0r246o?at_medium=RSS&at_campaign=rss",
      "title": "Heatwave prompts Italy's delivery riders to strike for extra rights",
      "source": "",
      "url": "",
      "published": "",
      "classifier_fallback": false,
      "priority_score": -0.09364312669105827,
      "contest_score": 2.5496661126950713,
      "category": "background_noise",
      "polarity": 1,
      "sign_agreement": 1.0,
      "central_tendency": 0.3801750456903797,
      "contestedness": 0.16698842257655805,
      "impact": 0.545,
      "top_clusters": {
        "expression_oriented": 0.6299571914957977,
        "care_oriented": 0.5924492517285647
      },
      "bottom_clusters": {
        "sovereignty_order_oriented": 0.1059042226876808
      },
      "cluster_means": {
        "survival_focused": 0.17820679357649077,
        "stability_seeking": 0.2698797171119947,
        "achievement_oriented": 0.21176636685217376,
        "care_oriented": 0.5924492517285647,
        "knowledge_oriented": 0.5454307663551198,
        "governance_oriented": 0.4254608291520066,
        "sovereignty_order_oriented": 0.1059042226876808,
        "expression_oriented": 0.6299571914957977,
        "ecosystem_oriented": 0.46252027225358866
      },
      "priority_raw": 0.12431723994075415,
      "contest_raw": 0.09100869030422415
    },
    {
      "signal_id": "https://www.bbc.co.uk/news/articles/cx2w2k3vklgo?at_medium=RSS&at_campaign=rss",
      "title": "Sierra Leone drops treason charge against ex-president over attempted coup",
      "source": "",
      "url": "",
      "published": "",
      "classifier_fallback": false,
      "priority_score": -0.12548646477045775,
      "contest_score": -1.1315239241160353,
      "category": "background_noise",
      "polarity": 1,
      "sign_agreement": 1.0,
      "central_tendency": 0.4864301962800547,
      "contestedness": 0.012728599700488341,
      "impact": 0.495,
      "top_clusters": {
        "stability_seeking": 0.5137847394378801,
        "achievement_oriented": 0.5092358298042656
      },
      "bottom_clusters": {
        "ecosystem_oriented": 0.4252045326279138
      },
      "cluster_means": {
        "survival_focused": 0.5010561397373917,
        "stability_seeking": 0.5137847394378801,
        "achievement_oriented": 0.5092358298042656,
        "care_oriented": 0.4841028086528224,
        "knowledge_oriented": 0.5045672672513503,
        "governance_oriented": 0.4599853568221999,
        "sovereignty_order_oriented": 0.4763295530196611,
        "expression_oriented": 0.5036055391670073,
        "ecosystem_oriented": 0.4252045326279138
      },
      "priority_raw": 0.12039147357931353,
      "contest_raw": 0.006300656851741729
    },
    {
      "signal_id": "https://www.bbc.co.uk/news/articles/cd959q11g54o?at_medium=RSS&at_campaign=rss",
      "title": "More people around the world now favour China over the US, Pew study suggests",
      "source": "",
      "url": "",
      "published": "",
      "classifier_fallback": false,
      "priority_score": -0.16846873209351831,
      "contest_score": -0.9031019648563278,
      "category": "background_noise",
      "polarity": 1,
      "sign_agreement": 1.0,
      "central_tendency": 0.5587012532480669,
      "contestedness": 0.02244055354347263,
      "impact": 0.515,
      "top_clusters": {
        "achievement_oriented": 0.6175306524626333,
        "stability_seeking": 0.5790952824201957
      },
      "bottom_clusters": {
        "ecosystem_oriented": 0.5271353205094655
      },
      "cluster_means": {
        "survival_focused": 0.5311453152168433,
        "stability_seeking": 0.5790952824201957,
        "achievement_oriented": 0.6175306524626333,
        "care_oriented": 0.5564471887082583,
        "knowledge_oriented": 0.5696895192581397,
        "governance_oriented": 0.5531143915001435,
        "sovereignty_order_oriented": 0.5340066351647856,
        "expression_oriented": 0.5601469739921372,
        "ecosystem_oriented": 0.5271353205094655
      },
      "priority_raw": 0.1150924581691018,
      "contest_raw": 0.011556885074888404
    },
    {
      "signal_id": "https://www.bbc.co.uk/news/articles/c8929jv8kdzo?at_medium=RSS&at_campaign=rss",
      "title": "Russian attacks kill eight as Ukraine hits Black Sea oil tankers",
      "source": "",
      "url": "",
      "published": "",
      "classifier_fallback": false,
      "priority_score": -0.40125961903886065,
      "contest_score": 0.1703438706675914,
      "category": "background_noise",
      "polarity": 1,
      "sign_agreement": 1.0,
      "central_tendency": 0.17559577840573778,
      "contestedness": 0.044217069057713,
      "impact": 0.8200000000000001,
      "top_clusters": {
        "expression_oriented": 0.2880752818343226,
        "knowledge_oriented": 0.26384963394358985
      },
      "bottom_clusters": {
        "survival_focused": 0.07229915807020118
      },
      "cluster_means": {
        "survival_focused": 0.07229915807020118,
        "stability_seeking": 0.11078649023228732,
        "achievement_oriented": 0.1995383434028797,
        "care_oriented": 0.15413200207254546,
        "knowledge_oriented": 0.26384963394358985,
        "governance_oriented": 0.1553212743451667,
        "sovereignty_order_oriented": 0.13821590607363468,
        "expression_oriented": 0.2880752818343226,
        "ecosystem_oriented": 0.19814391567701245
      },
      "priority_raw": 0.086393122975623,
      "contest_raw": 0.036257996627324665
    }
  ],
  "mood": {
    "score": 0.04065604156384353,
    "label": "cautious",
    "contested_share": 0.0,
    "emoji": "🟡"
  },
  "root_causes": [
    {
      "id": "https://www.bbc.co.uk/news/articles/cvg7g2z4pv3o?at_medium=RSS&at_campaign=rss",
      "rank": 1,
      "target": "French MPs approve assisted dying law with strict rules after years of argument",
      "title": "French MPs approve assisted dying law with strict rules after years of argument",
      "name": "French MPs approve assisted dying law with strict rules after years of argument",
      "root_cause": "French MPs approve assisted dying law with strict rules after years of argument",
      "severity": "low",
      "category": "background_noise",
      "priority_score": 2.70085512164684,
      "contest_score": -1.091510451905363,
      "contestedness": 0.01213682135019356,
      "mood": "↗ positive",
      "rationale": "Classified as Background Noise with ↗ positive ensemble direction and strongest pull from expression_oriented, knowledge_oriented.",
      "signal_count": 1,
      "signals": [
        "French MPs approve assisted dying law with strict rules after years of argument"
      ],
      "timeline": "1-4 weeks",
      "intervention": "Monitor the structural drivers and prepare targeted mitigations around the exposed subsystem.",
      "prediction": "Momentum around French MPs approve assisted dying law with strict rules after years of argument is likely to compound if current conditions hold.",
      "falsification": "Signals tied to French MPs approve assisted dying law with strict rules after years of argument fade or reverse without spillover."
    },
    {
      "id": "https://www.bbc.co.uk/news/articles/c2dydj1wp93o?at_medium=RSS&at_campaign=rss",
      "rank": 2,
      "target": "Trump pays writer E Jean Carroll $5m in damages over sexual abuse and defamation",
      "title": "Trump pays writer E Jean Carroll $5m in damages over sexual abuse and defamation",
      "name": "Trump pays writer E Jean Carroll $5m in damages over sexual abuse and defamation",
      "root_cause": "Trump pays writer E Jean Carroll $5m in damages over sexual abuse and defamation",
      "severity": "low",
      "category": "background_noise",
      "priority_score": 1.8580981689157126,
      "contest_score": -0.9313853555661555,
      "contestedness": 0.018026536642711366,
      "mood": "↗ positive",
      "rationale": "Classified as Background Noise with ↗ positive ensemble direction and strongest pull from knowledge_oriented, expression_oriented.",
      "signal_count": 1,
      "signals": [
        "Trump pays writer E Jean Carroll $5m in damages over sexual abuse and defamation"
      ],
      "timeline": "1-4 weeks",
      "intervention": "Monitor the structural drivers and prepare targeted mitigations around the exposed subsystem.",
      "prediction": "Momentum around Trump pays writer E Jean Carroll $5m in damages over sexual abuse and defamation is likely to compound if current conditions hold.",
      "falsification": "Signals tied to Trump pays writer E Jean Carroll $5m in damages over sexual abuse and defamation fade or reverse without spillover."
    },
    {
      "id": "https://www.bbc.co.uk/news/articles/c1eye5320g5o?at_medium=RSS&at_campaign=rss",
      "rank": 3,
      "target": "Venezuela government to launch formal talks with opposition members",
      "title": "Venezuela government to launch formal talks with opposition members",
      "name": "Venezuela government to launch formal talks with opposition members",
      "root_cause": "Venezuela government to launch formal talks with opposition members",
      "severity": "low",
      "category": "background_noise",
      "priority_score": 1.6973943497202002,
      "contest_score": -0.2639507079054021,
      "contestedness": 0.04775349832893605,
      "mood": "↗ positive",
      "rationale": "Classified as Background Noise with ↗ positive ensemble direction and strongest pull from governance_oriented, stability_seeking.",
      "signal_count": 1,
      "signals": [
        "Venezuela government to launch formal talks with opposition members"
      ],
      "timeline": "1-4 weeks",
      "intervention": "Monitor the structural drivers and prepare targeted mitigations around the exposed subsystem.",
      "prediction": "Momentum around Venezuela government to launch formal talks with opposition members is likely to compound if current conditions hold.",
      "falsification": "Signals tied to Venezuela government to launch formal talks with opposition members fade or reverse without spillover."
    },
    {
      "id": "https://www.bbc.co.uk/news/articles/c17y7ykzgrgo?at_medium=RSS&at_campaign=rss",
      "rank": 4,
      "target": "Boss of fake government agency arrested in Nigeria after weeks on the run",
      "title": "Boss of fake government agency arrested in Nigeria after weeks on the run",
      "name": "Boss of fake government agency arrested in Nigeria after weeks on the run",
      "root_cause": "Boss of fake government agency arrested in Nigeria after weeks on the run",
      "severity": "low",
      "category": "background_noise",
      "priority_score": 1.1199508766040707,
      "contest_score": -0.4069012431470118,
      "contestedness": 0.05105551718162049,
      "mood": "↗ positive",
      "rationale": "Classified as Background Noise with ↗ positive ensemble direction and strongest pull from governance_oriented, stability_seeking.",
      "signal_count": 1,
      "signals": [
        "Boss of fake government agency arrested in Nigeria after weeks on the run"
      ],
      "timeline": "1-4 weeks",
      "intervention": "Monitor the structural drivers and prepare targeted mitigations around the exposed subsystem.",
      "prediction": "Momentum around Boss of fake government agency arrested in Nigeria after weeks on the run is likely to compound if current conditions hold.",
      "falsification": "Signals tied to Boss of fake government agency arrested in Nigeria after weeks on the run fade or reverse without spillover."
    },
    {
      "id": "https://www.bbc.co.uk/news/articles/cjrgrgx2d9qo?at_medium=RSS&at_campaign=rss",
      "rank": 5,
      "target": "Air India crash report likely to be ready in October, say investigators",
      "title": "Air India crash report likely to be ready in October, say investigators",
      "name": "Air India crash report likely to be ready in October, say investigators",
      "root_cause": "Air India crash report likely to be ready in October, say investigators",
      "severity": "low",
      "category": "background_noise",
      "priority_score": 0.19969084019705347,
      "contest_score": 1.8722841713640797,
      "contestedness": 0.08978740864219059,
      "mood": "↗ positive",
      "rationale": "Classified as Background Noise with ↗ positive ensemble direction and strongest pull from expression_oriented, knowledge_oriented.",
      "signal_count": 1,
      "signals": [
        "Air India crash report likely to be ready in October, say investigators"
      ],
      "timeline": "1-4 weeks",
      "intervention": "Monitor the structural drivers and prepare targeted mitigations around the exposed subsystem.",
      "prediction": "Momentum around Air India crash report likely to be ready in October, say investigators is likely to compound if current conditions hold.",
      "falsification": "Signals tied to Air India crash report likely to be ready in October, say investigators fade or reverse without spillover."
    }
  ],
  "predictions": [],
  "narrative": "🟡 **Mood: Cautious** — Today's signals suggest incremental progress in governance and stability, but contested dynamics persist across geopolitical and societal fronts.\n\nThe structural pattern of the day reflects a cautious optimism, with several signals pointing to positive developments in governance and rule of law. **French MPs' approval of an assisted dying law** marks a significant societal shift after years of debate, signaling progress in legislative clarity on complex ethical issues. Similarly, **Venezuela's formal talks between government and opposition** suggest a potential step toward resolving long-standing political instability. These developments highlight governance-oriented momentum, but their broader implications remain uncertain, particularly in contested environments.\n\n**Why these signals matter:** The French assisted dying law is emblematic of a broader trend toward addressing divisive societal debates through structured legislative frameworks. Its high expression and knowledge-oriented scores suggest robust public discourse and institutional engagement, which could serve as a model for other nations grappling with similar ethical dilemmas. Meanwhile, Venezuela's talks, while promising, are fragile given the contestedness of the signal and the country's history of stalled negotiations. The arrest of a fake government agency leader in Nigeria underscores the importance of rule of law in combating corruption and stabilizing governance, though its lower priority score suggests limited ripple effects beyond the immediate region.\n\n**Contested signals:** The **Air India crash report**, while positive in its trajectory, reflects high contestedness due to its speculative nature. The report's anticipated release in October introduces uncertainty, as its findings could either reinforce aviation safety measures or expose systemic failures. Similarly, geopolitical tensions around Iran's threats to block trade routes and Trump's retreat on Hormuz tolls highlight speculative undertones, with limited immediate actionable outcomes. These signals should be monitored for shifts in direction or escalation.\n\n**Longer-term trajectories:** The signals collectively point to a slow recalibration of governance and stability in key regions. Venezuela's dialogue could pave the way for broader reconciliation if sustained, while France's legislative progress may influence global discourse on assisted dying laws. However, contested signals around Iran, Ukraine, and Hong Kong suggest persistent volatility in geopolitical and human rights domains, underscoring the need for vigilance in tracking these flashpoints.\n\n**What to watch next:** Focus on the outcomes of Venezuela's talks and the implementation of France's assisted dying law for signs of structural progress. Monitor contested signals like the Air India crash report and Iran's trade route threats for potential shifts in narrative or escalation. Additionally, keep an eye on geopolitical developments in Ukraine and Hong Kong, as these remain critical pressure points with broader implications for regional stability.",
  "noise_filtered": [
    "French MPs approve assisted dying law with strict rules after years of argument",
    "Trump pays writer E Jean Carroll $5m in damages over sexual abuse and defamation",
    "Venezuela government to launch formal talks with opposition members",
    "Boss of fake government agency arrested in Nigeria after weeks on the run",
    "Air India crash report likely to be ready in October, say investigators",
    "Special police team to investigate killing of an anti-migrant leader in South Africa",
    "Heatwave prompts Italy's delivery riders to strike for extra rights",
    "Sierra Leone drops treason charge against ex-president over attempted coup",
    "More people around the world now favour China over the US, Pew study suggests",
    "Russian attacks kill eight as Ukraine hits Black Sea oil tankers",
    "Diamond giant De Beers halts work at flagship South African mine as demand plummets",
    "Israeli strike on police post in north Gaza kills seven, officials say",
    "Trump retreat over Hormuz tolls suggests he is struggling to end Iran war",
    "Iran threatens to block more trade routes as US launches fresh strikes",
    "Italy's Meloni suffers surprise setback in close vote on electoral reform",
    "China economic growth falls sharply, missing target",
    "Seven Britons among those killed in Spain wildfires",
    "Rastafarians in Kenya fail in bid to get cannabis legalised for religious purposes",
    "China detains US scientist who studied North Korea nuclear tests",
    "Five arrested after Hong Kong police raid independent bookshops"
  ],
  "matured_predictions": [],
  "delta": {
    "is_first_run": false,
    "new_convergent": [],
    "new_contested": [],
    "removed_priorities": [
      {
        "title": "EU bans gold imports from Sudan to curb money financing the war",
        "reason": "No longer in today's news feed — story left the RSS cycle"
      },
      {
        "title": "US judge voids Donald Trump's $1.8bn settlement with IRS that gave him immunity from tax audits",
        "reason": "No longer in today's news feed — story left the RSS cycle"
      },
      {
        "title": "Hungary parliament votes to remove president from office",
        "reason": "No longer in today's news feed — story left the RSS cycle"
      },
      {
        "title": "US burrito giant Chipotle opening first outlet in Mexico",
        "reason": "No longer in today's news feed — story left the RSS cycle"
      },
      {
        "title": "Australian police reveal unseen photos 25 years after British backpacker murder",
        "reason": "No longer in today's news feed — story left the RSS cycle"
      },
      {
        "title": "Bangkok fire investigation finds locked doors and flammable decor as deaths climb to 30",
        "reason": "No longer in today's news feed — story left the RSS cycle"
      },
      {
        "title": "Trump scraps threat of 20% fee on Hormuz cargo as US resumes blockade of Iran ports",
        "reason": "No longer in today's news feed — story left the RSS cycle"
      },
      {
        "title": "'If we die, we die together': Wife of man nearly sucked out of Ryanair plane speaks of ordeal",
        "reason": "No longer in today's news feed — story left the RSS cycle"
      },
      {
        "title": "Health fears as frail Indian activist on hunger strike loses 8.2kg",
        "reason": "No longer in today's news feed — story left the RSS cycle"
      },
      {
        "title": "Singapore court orders Bloomberg to pay $356,000 to ministers in defamation case",
        "reason": "No longer in today's news feed — story left the RSS cycle"
      },
      {
        "title": "How US commerce secretary's Epstein links were uncovered by British whistleblower",
        "reason": "No longer in today's news feed — story left the RSS cycle"
      },
      {
        "title": "Identity of Sydney daycare worker facing 329 child abuse offences revealed",
        "reason": "No longer in today's news feed — story left the RSS cycle"
      },
      {
        "title": "Colombian national killed by ICE agent during operation in Maine",
        "reason": "No longer in today's news feed — story left the RSS cycle"
      },
      {
        "title": "Strait of Hormuz 'faultline' exposes weakness of the US-Iran deal",
        "reason": "No longer in today's news feed — story left the RSS cycle"
      },
      {
        "title": "Bison rams grandfather in Yellowstone Park, knocking him metres into the air",
        "reason": "No longer in today's news feed — story left the RSS cycle"
      },
      {
        "title": "Yemen's Houthis launch missiles at Saudi Arabia after strikes on Sanaa airport",
        "reason": "No longer in today's news feed — story left the RSS cycle"
      },
      {
        "title": "Tyrannosaurus rex most expensive dinosaur ever sold",
        "reason": "No longer in today's news feed — story left the RSS cycle"
      }
    ],
    "category_changes": [],
    "priority_score_changes": [
      "Israeli strike on police post in north Gaza kills seven, officials say: -0.69 → -0.42"
    ],
    "mood_shift": "",
    "structural_shifts": [
      "Priority score movement — Israeli strike on police post in north Gaza kills seven, officials say: -0.69 → -0.42"
    ],
    "continuing_priorities": [
      "Trump pays writer E Jean Carroll $5m in damages over sexual abuse and defamation",
      "Diamond giant De Beers halts work at flagship South African mine as demand plummets",
      "Israeli strike on police post in north Gaza kills seven, officials say"
    ],
    "new_stories": 17,
    "carried_stories": 3,
    "total_stories": 20,
    "summary": "17 priorities dropped: EU bans gold imports from Sudan to curb money financing the war (No longer in today's news feed — story left the RSS cycle); US judge voids Donald Trump's $1.8bn settlement with IRS that gave him immunity from tax audits (No longer in today's news feed — story left the RSS cycle); Hungary parliament votes to remove president from office (No longer in today's news feed — story left the RSS cycle); US burrito giant Chipotle opening first outlet in Mexico (No longer in today's news feed — story left the RSS cycle); Australian police reveal unseen photos 25 years after British backpacker murder (No longer in today's news feed — story left the RSS cycle); Bangkok fire investigation finds locked doors and flammable decor as deaths climb to 30 (No longer in today's news feed — story left the RSS cycle); Trump scraps threat of 20% fee on Hormuz cargo as US resumes blockade of Iran ports (No longer in today's news feed — story left the RSS cycle); 'If we die, we die together': Wife of man nearly sucked out of Ryanair plane speaks of ordeal (No longer in today's news feed — story left the RSS cycle); Health fears as frail Indian activist on hunger strike loses 8.2kg (No longer in today's news feed — story left the RSS cycle); Singapore court orders Bloomberg to pay $356,000 to ministers in defamation case (No longer in today's news feed — story left the RSS cycle); How US commerce secretary's Epstein links were uncovered by British whistleblower (No longer in today's news feed — story left the RSS cycle); Identity of Sydney daycare worker facing 329 child abuse offences revealed (No longer in today's news feed — story left the RSS cycle); Colombian national killed by ICE agent during operation in Maine (No longer in today's news feed — story left the RSS cycle); Strait of Hormuz 'faultline' exposes weakness of the US-Iran deal (No longer in today's news feed — story left the RSS cycle); Bison rams grandfather in Yellowstone Park, knocking him metres into the air (No longer in today's news feed — story left the RSS cycle); Yemen's Houthis launch missiles at Saudi Arabia after strikes on Sanaa airport (No longer in today's news feed — story left the RSS cycle); Tyrannosaurus rex most expensive dinosaur ever sold (No longer in today's news feed — story left the RSS cycle) · Priority intensity moved: Israeli strike on police post in north Gaza kills seven, officials say: -0.69 → -0.42 · Structural shifts: Priority score movement — Israeli strike on police post in north Gaza kills seven, officials say: -0.69 → -0.42 · Signal freshness: 17 new, 3 carried, 20 total"
  }
}